{
  "colors": {
    "darkBlue100": "#162740",
    "darkBlue090": "#243853",
    "darkBlue080": "#555E74",
    "darkBlue070": "#6E7D8D",
    "darkBlue060": "#808E99",
    "darkBlue050": "#96A29B",
    "darkBlue040": "#BBC3C9",
    "darkBlue030": "#E4E4E4",
    "darkBlue020": "#EBEBEB",
    "darkBlue010": "#F4F4F4",

    "blue005": "#F0F3FF",

    "inkBrand010": "{{colors.blue040}}",
    "inkBrand020": "{{colors.blue080}}",
    "inkBrand030": "{{colors.teal050}}",
    "inkWhiteSubtle": "{{colors.whiteTint080}}",
    "inkWhiteContrast": "{{colors.white}}",

    "interface020": "{{colors.darkBlue010}}",
    "interface030": "{{colors.darkBlue020}}",
    "interface040": "{{colors.darkBlue030}}",
    "interface050": "{{colors.darkBlue040}}",
    "interface060": "{{colors.darkBlue100}}",

    "interactivePrimary010": "{{colors.blue010}}",
    "interactivePrimary020": "{{colors.blue020}}",
    "interactivePrimary030": "{{colors.blue040}}",
    "interactivePrimary040": "{{colors.blue060}}",
    "interactivePrimary050": "{{colors.blue080}}",

    "interactiveSecondary010": "{{colors.neutral020}}",
    "interactiveSecondary020": "{{colors.neutral040}}",
    "interactiveSecondary030": "{{colors.neutral080}}",
    "interactiveSecondary040": "{{colors.neutral090}}",
    "interactiveSecondary050": "{{colors.neutral100}}",
    

    "interfaceBrand010": "{{colors.blue020}}",
    "interfaceBrand020": "{{colors.blue030}}",
    "interfaceBrand030": "{{colors.blue040}}",
    "interfaceBrand040": "{{colors.blue060}}",
    "interfaceBrand050": "{{colors.blue080}}",
    "interfaceBrand060": "{{colors.teal050}}",

    "interfaceSkeleton010": "{{colors.darkBlue010}}",
    "interfaceSkeleton020": "{{colors.darkBlue020}}",

    "illustrationPalette010": "{{colors.blue010}}",
    "illustrationPalette020": "{{colors.blue020}}",
    "illustrationPalette030": "{{colors.blue030}}",
    "illustrationPalette040": "{{colors.blue040}}",
    "illustrationPalette050": "{{colors.blue050}}",
    "illustrationPalette060": "{{colors.blue060}}",
    "illustrationPalette070": "{{colors.blue070}}",
    "illustrationPalette080": "{{colors.blue080}}",
    "illustrationPalette090": "{{colors.blue090}}",
    "illustrationPalette100": "{{colors.blue100}}",
    "illustrationHighlight010": "{{colors.blue040}}",
    "illustrationSubtle010": "{{colors.darkBlue060}}",
    "illustrationShadow010": "{{colors.blackTint030}}",
    "illustrationGradient010": "linear-gradient(0deg, rgba(10,10,10,0.00) 0%, rgba(10,10,10,1) 100%)",
    "illustrationGradient020": "linear-gradient(0deg, rgba(255,255,255,0.00) 0%, rgba(255,255,255,1) 100%)",
    "illustrationBackground010": "{{colors.blue005}}",
    "illustrationBackground020": "{{colors.darkBlue010}}",
    "illustrationBorder010": "{{colors.darkBlue020}}",
    "illustrationBorder020": "{{colors.darkBlue040}}",
    "illustrationDisabled": "{{colors.darkBlue020}}",
    "illustrationInterface010": "{{colors.white}}",
    "illustrationInterface020": "{{colors.blue010}}",
    "illustrationInterface030": "{{colors.blue020}}",
    "illustrationInterface040": "{{colors.blue030}}",
    "illustrationInterface050": "{{colors.blue040}}",
    "illustrationInterface060": "{{colors.blue050}}",
    "illustrationInterface070": "{{colors.blue060}}",
    "illustrationInterface080": "{{colors.blue070}}",
    "illustrationInterface090": "{{colors.blue080}}",
    "illustrationInterface100": "{{colors.blue090}}",
    "illustrationAnatomySubtle": "{{colors.blue020}}",
    "illustrationAnatomyBorder010": "{{colors.blue020}}",
    "illustrationAnatomyBorder020": "{{colors.blue070}}"
  }
}