[
  {
    "title": "Getting Started",
    "id": "/guides",
    "subNav": [
      {
        "title": "NewsKit",
        "page": true,
        "id": "/guides/getting-started-newskit"
      },
      {
        "title": "AMP",
        "page": true,
        "id": "/guides/getting-started-amp"
      },
      {
        "title": "Instrumentation",
        "page": true,
        "id": "/guides/getting-started-instrumentation"
      },
      {
        "title": "Component Generator",
        "page": true,
        "id": "/guides/getting-started-generator"
      }
    ]
  },
  {
    "title": "Theming",
    "id": "/theming",
    "subNav": [
      {
        "title": "Overview",
        "page": true,
        "id": "/theming/overview"
      },
      {
        "title": "Code",
        "page": true,
        "id": "/theming/code"
      },
      {
        "title": "Default Presets",
        "id": "/theming/default-presets",
        "subNav": [
          {
            "title": "Override in Theme",
            "page": true,
            "id": "/theming/default-presets/override-in-theme"
          },
          {
            "title": "Override Individual Components",
            "page": true,
            "id": "/theming/default-presets/override-individual-components"
          }
        ]
      },
      {
        "title": "StylePreset",
        "page": true,
        "id": "/theming/style-preset"
      }
    ]
  },
  {
    "title": "Foundations",
    "id": "/foundations",
    "subNav": [
      {
        "title": "Colours",
        "page": true,
        "id": "/foundations/colours"
      },
      {
        "title": "Icons",
        "page": true,
        "id": "/foundations/icons"
      },
      {
        "title": "Motion",
        "page": true,
        "id": "/foundations/motion"
      },
      {
        "title": "Spacing",
        "page": true,
        "id": "/foundations/spacing"
      },
      {
        "title": "Typography",
        "page": true,
        "id": "/foundations/typography"
      }
    ]
  },
  {
    "title": "Components",
    "id": "/components",
    "subNav": [
      {
        "title": "Aspect Ratio",
        "page": true,
        "id": "/components/aspect-ratio"
      },
      {
        "title": "Audio Player",
        "page": true,
        "id": "/components/audio-player"
      },
      {
        "title": "Block",
        "page": true,
        "id": "/components/block"
      },
      {
        "title": "Button",
        "page": true,
        "id": "/components/button"
      },
      {
        "title": "Byline",
        "page": true,
        "id": "/components/byline"
      },
      {
        "title": "Card",
        "page": true,
        "id": "/components/card"
      },
      {
        "title": "Consent",
        "page": true,
        "id": "/components/consent"
      },
      {
        "title": "Consent Settings Link",
        "page": true,
        "id": "/components/consent-settings-link"
      },
      {
        "title": "Date Time",
        "page": true,
        "id": "/components/date-time"
      },
      {
        "title": "Divider",
        "page": true,
        "id": "/components/divider"
      },
      {
        "title": "Flag",
        "page": true,
        "id": "/components/flag"
      },
      {
        "title": "Grid & Cell",
        "page": true,
        "id": "/components/grid"
      },
      {
        "title": "Headline",
        "page": true,
        "id": "/components/headline"
      },
      {
        "title": "Image",
        "page": true,
        "id": "/components/image"
      },
      {
        "title": "Link",
        "page": true,
        "id": "/components/link"
      },
      {
        "title": "Ordered List",
        "page": true,
        "id": "/components/ordered-list"
      },
      {
        "title": "Scroll",
        "page": true,
        "id": "/components/scroll"
      },
      {
        "title": "Share Bar",
        "page": true,
        "id": "/components/share-bar"
      },
      {
        "title": "Slider",
        "page": true,
        "id": "/components/slider"
      },
      {
        "title": "Stack & Stack Child",
        "page": true,
        "id": "/components/stack"
      },
      {
        "title": "Standfirst",
        "page": true,
        "id": "/components/standfirst"
      },
      {
        "title": "Tab",
        "page": true,
        "id": "/components/tab"
      },
      {
        "title": "Tag",
        "page": true,
        "id": "/components/tag"
      },
      {
        "title": "Tealium",
        "page": true,
        "id": "/components/tealium"
      },
      {
        "title": "Text Block",
        "page": true,
        "id": "/components/text-block"
      },
      {
        "title": "Title Bar",
        "page": true,
        "id": "/components/title-bar"
      },
      {
        "title": "Unordered List",
        "page": true,
        "id": "/components/unordered-list"
      },
      {
        "title": "Visibility",
        "page": true,
        "id": "/components/visibility"
      },
      {
        "title": "Volume Control",
        "page": true,
        "id": "/components/volume-control"
      }
    ]
  },
  {
    "title": "Utilities",
    "id": "/utils",
    "subNav": [
      {
        "title": "Code Helpers",
        "id": "/utils/code-helpers",
        "subNav": [
          {
            "title": "css",
            "page": true,
            "id": "/utils/code-helpers/css"
          },
          {
            "title": "getBorderFromTheme",
            "page": true,
            "id": "/utils/code-helpers/get-border-from-theme"
          },
          {
            "title": "getBuiId",
            "page": true,
            "id": "/utils/code-helpers/get-bui-id"
          },
          {
            "title": "getColorFromTheme",
            "page": true,
            "id": "/utils/code-helpers/get-color-from-theme"
          },
          {
            "title": "getDeviceQueryFromTheme",
            "page": true,
            "id": "/utils/code-helpers/get-device-query-from-theme"
          },
          {
            "title": "getFontsFromTheme",
            "page": true,
            "id": "/utils/code-helpers/get-fonts-from-theme"
          },
          {
            "title": "getMediaQueryFromTheme",
            "page": true,
            "id": "/utils/code-helpers/get-media-query-from-theme"
          },
          {
            "title": "getMotionFromTheme",
            "page": true,
            "id": "/utils/code-helpers/get-motion-from-theme"
          },
          {
            "title": "getShadowFromTheme",
            "page": true,
            "id": "/utils/code-helpers/get-shadow-from-theme"
          },
          {
            "title": "getSizingFromTheme",
            "page": true,
            "id": "/utils/code-helpers/get-sizing-from-theme"
          },
          {
            "title": "getStylePresetFromTheme",
            "page": true,
            "id": "/utils/code-helpers/get-style-preset-from-theme"
          },
          {
            "title": "getTypographyPresetFromTheme",
            "page": true,
            "id": "/utils/code-helpers/get-typography-preset-from-theme"
          }
        ]
      }
    ]
  },
  {
    "title": "Feedback",
    "page": true,
    "id": "/feedback"
  }
]